xtdamo/__init__.py
xtdamo/apiproxy.py
xtdamo/config.py
xtdamo/coreengine.py
xtdamo/damo.py
xtdamo/dependencies.py
xtdamo/enum_wind.py
xtdamo/key.py
xtdamo/mouse.py
xtdamo/regsvr.py
xtdamo/secure_config.py
xtdamo/time_utils.py
xtdamo-0.2.0.dist-info/licenses/LICENSE
xtdamo-0.2.0.dist-info/METADATA
xtdamo-0.2.0.dist-info/WHEEL
xtdamo-0.2.0.dist-info/top_level.txt
xtdamo-0.2.0.dist-info/RECORD
