Metadata-Version: 2.4
Name: xtdamo
Version: 0.2.0
Summary: 基于大漠插件的Python自动化封装库
Author-email: sandorn <sandorn@live.cn>
License: MIT
Project-URL: Homepage, https://github.com/sandorn/xtdamo
Project-URL: Repository, https://github.com/sandorn/xtdamo
Project-URL: Issues, https://github.com/sandorn/xtdamo/issues
Keywords: automation,dm-plugin,mouse,keyboard,image-recognition
Classifier: Development Status :: 4 - Beta
Classifier: Intended Audience :: Developers
Classifier: License :: OSI Approved :: MIT License
Classifier: Programming Language :: Python :: 3
Classifier: Programming Language :: Python :: 3.8
Classifier: Programming Language :: Python :: 3.9
Classifier: Programming Language :: Python :: 3.10
Classifier: Programming Language :: Python :: 3.11
Classifier: Programming Language :: Python :: 3.12
Classifier: Operating System :: Microsoft :: Windows
Classifier: Environment :: Win32 (MS Windows)
Requires-Python: >=3.8
License-File: LICENSE
Requires-Dist: cryptography>=46.0.3
Requires-Dist: pathlib>=1.0.1
Requires-Dist: pywin32>=306
Requires-Dist: xtlog>=0.1.9
Provides-Extra: dev
Dynamic: license-file
